Metadata-Version: 2.1
Name: odoo10-addon-shopinvader-backend-image-proxy
Version: 10.0.1.0.1
Summary: Add possibility to replace the image URL by the proxy url set on the SE backend
Home-page: http://www.akretion.com
Author: Akretion,ACSONE SA/NV
License: AGPL-3
Platform: UNKNOWN
Classifier: Programming Language :: Python
Classifier: Framework :: Odoo
Classifier: License :: OSI Approved :: GNU Affero General Public License v3
Requires-Python: ~=2.7
Requires-Dist: odoo10-addon-shopinvader-image
Requires-Dist: odoo (<10.1dev,>=10.0)
